crypto_trader/__init__.py
crypto_trader/binance.py
crypto_trader-0.0.2.dist-info/LICENSE
crypto_trader-0.0.2.dist-info/METADATA
crypto_trader-0.0.2.dist-info/WHEEL
crypto_trader-0.0.2.dist-info/top_level.txt
crypto_trader-0.0.2.dist-info/RECORD
